README.md
setup.cfg
setup.py
dylansdistributions/Binomialdistribution.py
dylansdistributions/Gaussiandistribution.py
dylansdistributions/Generaldistribution.py
dylansdistributions/__init__.py
dylansdistributions.egg-info/PKG-INFO
dylansdistributions.egg-info/SOURCES.txt
dylansdistributions.egg-info/dependency_links.txt
dylansdistributions.egg-info/not-zip-safe
dylansdistributions.egg-info/top_level.txt