Metadata-Version: 1.0
Name: dylansdistributions
Version: 0.1
Summary: Gaussian distributions
Home-page: UNKNOWN
Author: Dylan Rigney
Author-email: dylanrigney@hotmail.com
License: UNKNOWN
Platform: UNKNOWN
